pdebench/__init__.py
pdebench/data_download/download_direct.py
pdebench/data_download/download_easydataverse.py
pdebench/data_download/visualize_pdes.py
pdebench/data_gen/gen_diff_react.py
pdebench/data_gen/gen_diff_sorp.py
pdebench/data_gen/gen_ns_incomp.py
pdebench/data_gen/gen_radial_dam_break.py
pdebench/data_gen/plot.py
pdebench/data_gen/uploader.py
pdebench/data_gen/data_gen_NLE/Data_Merge.py
pdebench/data_gen/data_gen_NLE/utils.py
pdebench/data_gen/data_gen_NLE/AdvectionEq/advection_exact_Hydra.py
pdebench/data_gen/data_gen_NLE/AdvectionEq/advection_multi_solution_Hydra.py
pdebench/data_gen/data_gen_NLE/BurgersEq/burgers_Hydra.py
pdebench/data_gen/data_gen_NLE/BurgersEq/burgers_multi_solution_Hydra.py
pdebench/data_gen/data_gen_NLE/CompressibleFluid/CFD_Hydra.py
pdebench/data_gen/data_gen_NLE/CompressibleFluid/CFD_multi_Hydra.py
pdebench/data_gen/data_gen_NLE/ReactionDiffusionEq/reaction_diffusion_2D_multi_solution_Hydra.py
pdebench/data_gen/data_gen_NLE/ReactionDiffusionEq/reaction_diffusion_Hydra.py
pdebench/data_gen/data_gen_NLE/ReactionDiffusionEq/reaction_diffusion_multi_solution_Hydra.py
pdebench/data_gen/src/__init__.py
pdebench/data_gen/src/data_io.py
pdebench/data_gen/src/plots.py
pdebench/data_gen/src/pytorch_dataset.py
pdebench/data_gen/src/sim_diff_react.py
pdebench/data_gen/src/sim_diff_sorp.py
pdebench/data_gen/src/sim_ns_incomp_2d.py
pdebench/data_gen/src/sim_radial_dam_break.py
pdebench/data_gen/src/utils.py
pdebench/data_gen/src/_attic/grf.py
pdebench/models/analyse_result_forward.py
pdebench/models/analyse_result_inverse.py
pdebench/models/metrics.py
pdebench/models/train_models_forward.py
pdebench/models/train_models_inverse.py
pdebench/models/fno/fno.py
pdebench/models/fno/train.py
pdebench/models/fno/utils.py
pdebench/models/inverse/inverse.py
pdebench/models/inverse/train.py
pdebench/models/inverse/utils.py
pdebench/models/pinn/pde_definitions.py
pdebench/models/pinn/train.py
pdebench/models/pinn/utils.py
pdebench/models/unet/train.py
pdebench-0.1.0.dist-info/LICENSE.txt
pdebench-0.1.0.dist-info/METADATA
pdebench-0.1.0.dist-info/WHEEL
pdebench-0.1.0.dist-info/top_level.txt
pdebench-0.1.0.dist-info/RECORD
