Metadata-Version: 2.1
Name: pdebench
Version: 0.1.0
Summary: PDEBench: An Extensive Benchmark for Scientific Machine Learning
Author: Dan MacKinlay, Francesco Alesiani, Dirk Pflüger, Mathias Niepert
Author-email: Makoto Takamoto <Makoto.Takamoto@neclab.eu>, Timothy Praditia <timothy.praditia@iws.uni-stuttgart.de>, Raphael Leiteritz <raphael.leiteritz@ipvs.uni-stuttgart.de>
License: Except where otherwise stated this code is released under the MIT license.
Project-URL: Homepage, https://github.com/pdebench/PDEBenchm
Project-URL: Documentation, https://github.com/pdebench/PDEBench
Project-URL: Repository, https://github.com/pdebench/PDEBench
Requires-Python: <3.11,>=3.9
License-File: LICENSE.txt
Requires-Dist: scipy
Requires-Dist: matplotlib
Requires-Dist: h5py
Requires-Dist: pandas
Requires-Dist: python-dotenv
Requires-Dist: hydra-core
Requires-Dist: torch ~=1.13.0
Requires-Dist: torchvision ~=0.14.1
Requires-Dist: deepxde ~=1.1.3
Requires-Dist: pyro-ppl
Requires-Dist: tqdm
